witnessmess/__init__.py
witnessmess/_cm.py
witnessmess/_dm.py
witnessmess/_pi.py
witnessmess-0.4.3.dist-info/LICENSE
witnessmess-0.4.3.dist-info/METADATA
witnessmess-0.4.3.dist-info/WHEEL
witnessmess-0.4.3.dist-info/top_level.txt
witnessmess-0.4.3.dist-info/RECORD
