Metadata-Version: 2.1
Name: witnessmess
Version: 0.4.3
Summary: Witnessing multi-partite entanglement.
Home-page: https://provaznik.pro/witnessmess
Author: Jan Provaznik
Author-email: jan@provaznik.pro
License: LGPL
License-File: LICENSE
Requires-Dist: picos (>=2.4)
Requires-Dist: numpy
Requires-Dist: scipy
